{
    "set": "wef",
    "name": "Unchained Destroyer",
    "collector_number": -1,
    "rarity": "c",
    "type": "Creature — Demon Warrior",
    "png": "https://mtg.design/i/jpqj29.jpg",
    "back": "",
    "colors": "B",
    "cmc": "6",
    "pow": "5",
    "tou": "5",
    "text": "This spell costs {2} less to cast if an opponent's life total is less than half its starting life total.\n\nDragonform (Whenever this creature attacks, if defending player's life total is less than half its starting life total, this creature gets +1/+1 and flying until end of turn.)",
    "tokens": []
}